zalando_aws_cli/__init__.py
zalando_aws_cli/__main__.py
zalando_aws_cli/cli.py
zalando_aws_cli-1.2.12.61.dist-info/LICENSE
zalando_aws_cli-1.2.12.61.dist-info/METADATA
zalando_aws_cli-1.2.12.61.dist-info/WHEEL
zalando_aws_cli-1.2.12.61.dist-info/entry_points.txt
zalando_aws_cli-1.2.12.61.dist-info/top_level.txt
zalando_aws_cli-1.2.12.61.dist-info/RECORD
